{
  "/HomePage" : {
    "transaction" : "/HomePage",
    "sampleCount" : 5,
    "errorCount" : 0,
    "errorPct" : 0.0,
    "meanResTime" : 372.8,
    "medianResTime" : 319.0,
    "minResTime" : 261.0,
    "maxResTime" : 669.0,
    "pct1ResTime" : 669.0,
    "pct2ResTime" : 669.0,
    "pct3ResTime" : 669.0,
    "throughput" : 0.30923371884470285,
    "receivedKBytesPerSec" : 0.506732597872472,
    "sentKBytesPerSec" : 0.2566881455253881
  },
  "FlighBooking_T04_BookFlight" : {
    "transaction" : "FlighBooking_T04_BookFlight",
    "sampleCount" : 5,
    "errorCount" : 0,
    "errorPct" : 0.0,
    "meanResTime" : 431.4,
    "medianResTime" : 434.0,
    "minResTime" : 283.0,
    "maxResTime" : 607.0,
    "pct1ResTime" : 607.0,
    "pct2ResTime" : 607.0,
    "pct3ResTime" : 607.0,
    "throughput" : 0.3159757330637007,
    "receivedKBytesPerSec" : 0.5285187847573306,
    "sentKBytesPerSec" : 0.4375523334807887
  },
  "FlighBooking_T02_FlightFinder" : {
    "transaction" : "FlighBooking_T02_FlightFinder",
    "sampleCount" : 5,
    "errorCount" : 0,
    "errorPct" : 0.0,
    "meanResTime" : 274.0,
    "medianResTime" : 240.0,
    "minResTime" : 205.0,
    "maxResTime" : 433.0,
    "pct1ResTime" : 433.0,
    "pct2ResTime" : 433.0,
    "pct3ResTime" : 433.0,
    "throughput" : 0.3194479938665985,
    "receivedKBytesPerSec" : 0.5557895955788398,
    "sentKBytesPerSec" : 0.38308802389471
  },
  "Total" : {
    "transaction" : "Total",
    "sampleCount" : 20,
    "errorCount" : 0,
    "errorPct" : 0.0,
    "meanResTime" : 372.2,
    "medianResTime" : 323.0,
    "minResTime" : 205.0,
    "maxResTime" : 683.0,
    "pct1ResTime" : 662.8000000000002,
    "pct2ResTime" : 682.3,
    "pct3ResTime" : 683.0,
    "throughput" : 0.48618032428227625,
    "receivedKBytesPerSec" : 0.8500559107372925,
    "sentKBytesPerSec" : 0.5690303893088947
  },
  "FlighBooking_T01_HomePage" : {
    "transaction" : "FlighBooking_T01_HomePage",
    "sampleCount" : 5,
    "errorCount" : 0,
    "errorPct" : 0.0,
    "meanResTime" : 372.8,
    "medianResTime" : 319.0,
    "minResTime" : 261.0,
    "maxResTime" : 669.0,
    "pct1ResTime" : 669.0,
    "pct2ResTime" : 669.0,
    "pct3ResTime" : 669.0,
    "throughput" : 0.30759766225776686,
    "receivedKBytesPerSec" : 0.5040516379575516,
    "sentKBytesPerSec" : 0.25533009074131036
  },
  "/confirmation.php" : {
    "transaction" : "/confirmation.php",
    "sampleCount" : 5,
    "errorCount" : 0,
    "errorPct" : 0.0,
    "meanResTime" : 431.4,
    "medianResTime" : 434.0,
    "minResTime" : 283.0,
    "maxResTime" : 607.0,
    "pct1ResTime" : 607.0,
    "pct2ResTime" : 607.0,
    "pct3ResTime" : 607.0,
    "throughput" : 0.31599570245844655,
    "receivedKBytesPerSec" : 0.528552186690261,
    "sentKBytesPerSec" : 0.43757998641218476
  },
  "FlighBooking_T03_SelectFlight" : {
    "transaction" : "FlighBooking_T03_SelectFlight",
    "sampleCount" : 5,
    "errorCount" : 0,
    "errorPct" : 0.0,
    "meanResTime" : 410.6,
    "medianResTime" : 365.0,
    "minResTime" : 221.0,
    "maxResTime" : 683.0,
    "pct1ResTime" : 683.0,
    "pct2ResTime" : 683.0,
    "pct3ResTime" : 683.0,
    "throughput" : 0.314346787375833,
    "receivedKBytesPerSec" : 0.6106431928203193,
    "sentKBytesPerSec" : 0.3984591113416321
  },
  "/purchase.php" : {
    "transaction" : "/purchase.php",
    "sampleCount" : 5,
    "errorCount" : 0,
    "errorPct" : 0.0,
    "meanResTime" : 410.6,
    "medianResTime" : 365.0,
    "minResTime" : 221.0,
    "maxResTime" : 683.0,
    "pct1ResTime" : 683.0,
    "pct2ResTime" : 683.0,
    "pct3ResTime" : 683.0,
    "throughput" : 0.314346787375833,
    "receivedKBytesPerSec" : 0.6106431928203193,
    "sentKBytesPerSec" : 0.3984591113416321
  },
  "/reserve.php" : {
    "transaction" : "/reserve.php",
    "sampleCount" : 5,
    "errorCount" : 0,
    "errorPct" : 0.0,
    "meanResTime" : 274.0,
    "medianResTime" : 240.0,
    "minResTime" : 205.0,
    "maxResTime" : 433.0,
    "pct1ResTime" : 433.0,
    "pct2ResTime" : 433.0,
    "pct3ResTime" : 433.0,
    "throughput" : 0.3194479938665985,
    "receivedKBytesPerSec" : 0.5557895955788398,
    "sentKBytesPerSec" : 0.38308802389471
  }
}